fortytwo/__init__.py
fortytwo/client.py
fortytwo/config.py
fortytwo/default.py
fortytwo/json.py
fortytwo/py.typed
fortytwo/exceptions/__init__.py
fortytwo/exceptions/exceptions.py
fortytwo/logger/README.md
fortytwo/logger/__init__.py
fortytwo/logger/logger.py
fortytwo/request/__init__.py
fortytwo/request/authentication.py
fortytwo/request/handler.py
fortytwo/request/request.py
fortytwo/request/parameter/__init__.py
fortytwo/request/parameter/pagination.py
fortytwo/request/parameter/parameter.py
fortytwo/request/secret_manager/README.md
fortytwo/request/secret_manager/__init__.py
fortytwo/request/secret_manager/memory.py
fortytwo/request/secret_manager/secret_manager.py
fortytwo/request/secret_manager/vault.py
fortytwo/resources/README.md
fortytwo/resources/__init__.py
fortytwo/resources/custom.py
fortytwo/resources/model.py
fortytwo/resources/resource.py
fortytwo/resources/campus/README.md
fortytwo/resources/campus/__init__.py
fortytwo/resources/campus/campus.py
fortytwo/resources/campus/manager.py
fortytwo/resources/campus/resource.py
fortytwo/resources/campus/parameter/README.md
fortytwo/resources/campus/parameter/__init__.py
fortytwo/resources/campus/parameter/filter.py
fortytwo/resources/campus/parameter/range.py
fortytwo/resources/campus/parameter/sort.py
fortytwo/resources/campus_user/README.md
fortytwo/resources/campus_user/__init__.py
fortytwo/resources/campus_user/campus_user.py
fortytwo/resources/campus_user/manager.py
fortytwo/resources/campus_user/resource.py
fortytwo/resources/campus_user/parameter/README.md
fortytwo/resources/campus_user/parameter/__init__.py
fortytwo/resources/campus_user/parameter/filter.py
fortytwo/resources/campus_user/parameter/parameter.py
fortytwo/resources/campus_user/parameter/range.py
fortytwo/resources/campus_user/parameter/sort.py
fortytwo/resources/cursus/README.md
fortytwo/resources/cursus/__init__.py
fortytwo/resources/cursus/cursus.py
fortytwo/resources/cursus/manager.py
fortytwo/resources/cursus/resource.py
fortytwo_client-4.0.7.dist-info/METADATA
fortytwo_client-4.0.7.dist-info/WHEEL
fortytwo_client-4.0.7.dist-info/licenses/LICENSE
fortytwo_client-4.0.7.dist-info/RECORD
