Metadata-Version: 2.4
Name: fortytwo-client
Version: 4.0.7
Summary: A Python client library for the 42 School API
Project-URL: Homepage, https://github.com/lucas-ht/fortytwo-client
Project-URL: Documentation, https://github.com/lucas-ht/fortytwo-client#readme
Project-URL: Repository, https://github.com/lucas-ht/fortytwo-client.git
Project-URL: Bug Tracker, https://github.com/lucas-ht/fortytwo-client/issues
Author-email: lucas-ht <46166712+lucas-ht@users.noreply.github.com>
Maintainer-email: lucas-ht <46166712+lucas-ht@users.noreply.github.com>
License: MIT
License-File: LICENSE
Keywords: 42,api,client,school
Classifier: Development Status :: 4 - Beta
Classifier: Intended Audience :: Developers
Classifier: License :: OSI Approved :: MIT License
Classifier: Operating System :: OS Independent
Classifier: Programming Language :: Python :: 3
Classifier: Programming Language :: Python :: 3.12
Classifier: Programming Language :: Python :: 3.13
Classifier: Topic :: Internet :: WWW/HTTP :: Dynamic Content
Classifier: Topic :: Software Development :: Libraries :: Python Modules
Requires-Python: >=3.12
Requires-Dist: python-dateutil>=2.9.0.post0
Requires-Dist: pytz>=2025.2
Requires-Dist: requests>=2.32.5
